airsql/__init__.py
airsql/decorators.py
airsql/file.py
airsql/hooks.py
airsql/operators.py
airsql/sensors/__init__.py
airsql/sensors/bigquery.py
airsql/sensors/postgres.py
airsql/table.py
airsql/transfers/__init__.py
airsql/transfers/bigquery_postgres.py
airsql/transfers/gcs_postgres.py
airsql/transfers/postgres_bigquery.py
airsql/transfers/postgres_gcs.py
airsql-0.4.0.dist-info/WHEEL
airsql-0.4.0.dist-info/entry_points.txt
airsql-0.4.0.dist-info/METADATA
airsql-0.4.0.dist-info/RECORD
