Metadata-Version: 2.3
Name: airsql
Version: 0.4.0
Summary: A decorator-based SQL execution framework for Airflow
Keywords: airflow,sql,etl,data-engineering,bigquery,postgres
Author: 1cadumagalhaes
Author-email: 1cadumagalhaes <github@cadumagalhaes.dev>
License: MIT License
Classifier: Development Status :: 4 - Beta
Classifier: Intended Audience :: Developers
Classifier: License :: OSI Approved :: MIT License
Classifier: Operating System :: OS Independent
Classifier: Programming Language :: Python :: 3
Classifier: Programming Language :: Python :: 3.12
Classifier: Programming Language :: Python :: 3.13
Classifier: Topic :: Database
Classifier: Topic :: Software Development :: Libraries :: Python Modules
Classifier: Framework :: Apache Airflow
Requires-Dist: apache-airflow-providers-common-sql>=1.27.1
Requires-Dist: apache-airflow-providers-postgres>=6.2.0
Requires-Dist: apache-airflow[google,standard]>=3.0.0
Requires-Dist: pandas>=2.0.0
Requires-Dist: pydantic>=2.0.0
Requires-Dist: jinja2>=3.0.0
Maintainer: 1cadumagalhaes
Maintainer-email: 1cadumagalhaes <github@cadumagalhaes.dev>
Requires-Python: >=3.12
Project-URL: Changelog, https://github.com/1cadumagalhaes/airsql/releases
Project-URL: Documentation, https://github.com/1cadumagalhaes/airsql#readme
Project-URL: Homepage, https://github.com/1cadumagalhaes/airsql
Project-URL: Issues, https://github.com/1cadumagalhaes/airsql/issues
Project-URL: Repository, https://github.com/1cadumagalhaes/airsql
